flakeplus/__init__.py
flakeplus-1.1.0.dist-info/DESCRIPTION.rst
flakeplus-1.1.0.dist-info/entry_points.txt
flakeplus-1.1.0.dist-info/METADATA
flakeplus-1.1.0.dist-info/metadata.json
flakeplus-1.1.0.dist-info/RECORD
flakeplus-1.1.0.dist-info/top_level.txt
flakeplus-1.1.0.dist-info/WHEEL
